phigrade/__init__.py
phigrade/app.py
phigrade/compare.py
phigrade/gradescope_output.py
phigrade/phigrade.py
phigrade/server.py
phigrade-1.0.0.dist-info/LICENSE
phigrade-1.0.0.dist-info/METADATA
phigrade-1.0.0.dist-info/WHEEL
phigrade-1.0.0.dist-info/RECORD
