Metadata-Version: 2.3
Name: phigrade
Version: 1.0.0
Summary: A lightweight autograder where tests run locally and data is stored remotely
License: MIT
Keywords: autograder,education,grading
Author: Matt Gormley
Author-email: mgormley@cs.cmu.edu
Requires-Python: >=3.12,<4.0
Classifier: Programming Language :: Python :: 3
Classifier: License :: OSI Approved :: MIT License
Classifier: Operating System :: OS Independent
Provides-Extra: dev
Requires-Dist: fastapi (>=0.115.13,<0.116.0)
Requires-Dist: numpy (>=2.0.0,<3.0.0)
Requires-Dist: omegaconf (>=2.3.0,<3.0.0)
Requires-Dist: pydantic (>=2.11.7,<3.0.0)
Requires-Dist: pytest (>=8.4.1,<9.0.0) ; extra == "dev"
Requires-Dist: requests (>=2.32.4,<3.0.0)
Requires-Dist: tinydb (>=4.8.2,<5.0.0)
Requires-Dist: uvicorn (>=0.34.3,<0.35.0)
Project-URL: Repository, https://github.com/mld-instructors/phigrade
